[{"Title": "The Raven Scholar (Eternal Path Trilogy, #1)", "Author": " Antonia Hodgson", "Date": "Apr 17, 2025", "Link": "https://goodreads.com/book/show/212174157-the-raven-scholar", "Cover": "https://i.gr-assets.com/images/S/photo.goodreads.com/books/1744300189l/212174157.jpg"}, {"Title": "The Bright Years", "Author": " Sarah Damoff", "Date": "Apr 22, 2025", "Link": "https://goodreads.com/book/show/214152211-the-bright-years", "Cover": "https://i.gr-assets.com/images/S/photo.goodreads.com/books/1717697006l/214152211.jpg"}]