[{"Title": "Full Moon Over Freedom (Milagro Street, #2)", "Author": " Angelina M. Lopez", "Date": "Sep 05, 2023", "Link": "https://goodreads.com/book/show/63095149-full-moon-over-freedom", "Cover": "https://i.gr-assets.com/images/S/photo.goodreads.com/books/1680268696l/63095149.jpg"}, {"Title": "The Long Game (Long Game, #1)", "Author": " Elena Armas", "Date": "Sep 05, 2023", "Link": "https://goodreads.com/book/show/101144869-the-long-game", "Cover": "https://i.gr-assets.com/images/S/photo.goodreads.com/books/1687105546l/101144869.jpg"}]