[{"Title": "Intermezzo", "Author": " Sally Rooney", "Date": "Sep 24, 2024", "Link": "https://goodreads.com/book/show/208931300-intermezzo", "Cover": "https://i.gr-assets.com/images/S/photo.goodreads.com/books/1716387455l/208931300.jpg"}, {"Title": "The Slowest Burn", "Author": " Sarah Chamberlain", "Date": "Sep 24, 2024", "Link": "https://goodreads.com/book/show/203238086-the-slowest-burn", "Cover": "https://i.gr-assets.com/images/S/photo.goodreads.com/books/1705592412l/203238086.jpg"}, {"Title": "All I Want Is You", "Author": " Falon Ballard", "Date": "Sep 24, 2024", "Link": "https://goodreads.com/book/show/204316922-all-i-want-is-you", "Cover": "https://i.gr-assets.com/images/S/photo.goodreads.com/books/1711520290l/204316922.jpg"}, {"Title": "The Dating Countdown (Island Bites, #3)", "Author": " N.G. Peltier", "Date": "Sep 26, 2024", "Link": "https://goodreads.com/book/show/204412153-the-dating-countdown", "Cover": "https://i.gr-assets.com/images/S/photo.goodreads.com/books/1703767237l/204412153.jpg"}, {"Title": "Bad Reputation", "Author": " Emma Barry", "Date": "Oct 01, 2024", "Link": "https://goodreads.com/book/show/204221628-bad-reputation", "Cover": "https://i.gr-assets.com/images/S/photo.goodreads.com/books/1712610991l/204221628.jpg"}]